podaac/__init__.py
podaac/swot_ocean.py
podaac/utils.py
podaac-0.1.4.dist-info/LICENSE
podaac-0.1.4.dist-info/METADATA
podaac-0.1.4.dist-info/WHEEL
podaac-0.1.4.dist-info/top_level.txt
podaac-0.1.4.dist-info/RECORD
