Metadata-Version: 2.1
Name: podaac
Version: 0.1.4
Summary: Shorten the distance between data and human.
Home-page: https://github.com/podaac/podaacpy
Author: PO.DAAC
Author-email: podaac@podaac.jpl.nasa.gov
Classifier: Programming Language :: Python :: 3
Classifier: License :: OSI Approved :: MIT License
Classifier: Operating System :: OS Independent
License-File: LICENSE
Requires-Dist: numpy
Requires-Dist: scipy
Requires-Dist: xarray
Requires-Dist: pyresample
Requires-Dist: matplotlib
Requires-Dist: cartopy
Requires-Dist: pandas
Requires-Dist: h5py
Requires-Dist: netcdf4
Requires-Dist: dask
